earningtrader-0.1.0.dist-info/METADATA
earningtrader-0.1.0.dist-info/WHEEL
earningtrader-0.1.0.dist-info/licenses/LICENSE
earningtrader/.coverage
earningtrader/.pytest_cache/.gitignore
earningtrader/.pytest_cache/CACHEDIR.TAG
earningtrader/.pytest_cache/README.md
earningtrader/.pytest_cache/v/cache/nodeids
earningtrader/.pytest_cache/v/cache/stepwise
earningtrader/__init__.py
earningtrader/common/__init__.py
earningtrader/common/exceptions.py
earningtrader/controller/__init__.py
earningtrader/controller/_interface.py
earningtrader/controller/_logger/__init__.py
earningtrader/controller/_logger/_interface.py
earningtrader/controller/_logger/_python.py
earningtrader/controller/bernoulli_ts_simulator.py
earningtrader/data/__init__.py
earningtrader/data/acquisition/__init__.py
earningtrader/data/acquisition/_interface.py
earningtrader/data/acquisition/yfinance.py
earningtrader/data/preprocessing/__init__.py
earningtrader/data/preprocessing/_interface.py
earningtrader/data/preprocessing/preprocessor.py
earningtrader/model/__init__.py
earningtrader/model/_interface.py
earningtrader/model/bernoulli_ts.py
earningtrader/storage/__init__.py
earningtrader/storage/_interface.py
earningtrader/storage/shelve_storage.py
earningtrader/trader/__init__.py
earningtrader/trader/_interface.py
earningtrader/trader/simulation_trader.py
earningtrader-0.1.0.dist-info/RECORD
